jinja2-gcp-secret-manager/__init__.py
jinja2_gcp_secret_manager/__init__.py
jinja2_gcp_secret_manager-1.2.0.dist-info/LICENSE
jinja2_gcp_secret_manager-1.2.0.dist-info/METADATA
jinja2_gcp_secret_manager-1.2.0.dist-info/WHEEL
jinja2_gcp_secret_manager-1.2.0.dist-info/top_level.txt
jinja2_gcp_secret_manager-1.2.0.dist-info/RECORD
