Metadata-Version: 2.1
Name: jinja2-gcp-secret-manager
Version: 1.2.0
Summary: Jinja2 extension for fetching secrets GCP Secret Manager
Home-page: https://github.com/yashmehrotra/jinja2-gcp-secret-manager
Author: Yash Mehrotra
Author-email: yashmehrotra95@gmail.com
License: Apache 2.0
Platform: UNKNOWN
Classifier: Programming Language :: Python :: 3
Classifier: License :: OSI Approved :: MIT License
Classifier: Operating System :: OS Independent
Requires-Dist: Jinja2 (==2.11.3)
Requires-Dist: google-cloud-secret-manager (==2.2.0)
Requires-Dist: google-api-core[grpc] (==1.25.1)
Requires-Dist: grpc-google-iam-v1 (==0.12.3)
Requires-Dist: proto-plus (==1.13.0)
Requires-Dist: libcst (>=0.2.5)
Requires-Dist: protobuf (==3.14.0)
Requires-Dist: googleapis-common-protos (==1.52.0)
